kraken_browser/__init__.py
kraken_browser/kraken_browser.py
kraken_browser-0.0.3.dist-info/LICENSE.txt
kraken_browser-0.0.3.dist-info/METADATA
kraken_browser-0.0.3.dist-info/WHEEL
kraken_browser-0.0.3.dist-info/top_level.txt
kraken_browser-0.0.3.dist-info/RECORD
