Metadata-Version: 2.1
Name: kraken-browser
Version: 0.0.3
Summary: Kraken Browser
Home-page: https://github.com/tactik8/kraken_image_processing
Author: Tactik8
Author-email: info@tactik8.com
License: MIT
Platform: UNKNOWN
Classifier: License :: OSI Approved :: MIT License
Classifier: Programming Language :: Python :: 3
Classifier: Programming Language :: Python :: 3.8
License-File: LICENSE.txt
Requires-Dist: pyppeteer
Requires-Dist: aiohttp
Requires-Dist: free-proxy
